adafruit_cst8xx.py
adafruit_circuitpython_cst8xx-1.1.1.dist-info/licenses/LICENSE
adafruit_circuitpython_cst8xx-1.1.1.dist-info/METADATA
adafruit_circuitpython_cst8xx-1.1.1.dist-info/WHEEL
adafruit_circuitpython_cst8xx-1.1.1.dist-info/top_level.txt
adafruit_circuitpython_cst8xx-1.1.1.dist-info/RECORD
