Metadata-Version: 2.4
Name: adafruit-circuitpython-cst8xx
Version: 1.1.1
Summary: CST8xx capacitive touch driver for CircuitPython
Author-email: Adafruit Industries <circuitpython@adafruit.com>
License: MIT
Project-URL: Homepage, https://github.com/adafruit/Adafruit_CircuitPython_CST8XX
Keywords: adafruit,blinka,circuitpython,micropython,cst8xx,capacitive,touch,screen,display,touchscreenhardware
Classifier: Intended Audience :: Developers
Classifier: Topic :: Software Development :: Libraries
Classifier: Topic :: Software Development :: Embedded Systems
Classifier: Topic :: System :: Hardware
Classifier: License :: OSI Approved :: MIT License
Classifier: Programming Language :: Python :: 3
License-File: LICENSE
Requires-Dist: Adafruit-Blinka
Requires-Dist: adafruit-circuitpython-busdevice
Provides-Extra: optional
Dynamic: license-file
